bigtiger_admin_owl-0.0.1rc2.dist-info/DESCRIPTION.rst
bigtiger_admin_owl-0.0.1rc2.dist-info/METADATA
bigtiger_admin_owl-0.0.1rc2.dist-info/RECORD
bigtiger_admin_owl-0.0.1rc2.dist-info/WHEEL
bigtiger_admin_owl-0.0.1rc2.dist-info/metadata.json
bigtiger_admin_owl-0.0.1rc2.dist-info/top_level.txt
owl_admin/__init__.py
owl_admin/apps.py
owl_admin/forms/__init__.py
owl_admin/static/My97DatePicker/README.md
owl_admin/static/My97DatePicker/WdatePicker.js
owl_admin/static/My97DatePicker/calendar.js
owl_admin/static/My97DatePicker/lang/en.js
owl_admin/static/My97DatePicker/lang/zh-cn.js
owl_admin/static/My97DatePicker/lang/zh-tw.js
owl_admin/static/My97DatePicker/skin/WdatePicker.css
owl_admin/static/My97DatePicker/skin/datePicker.gif
owl_admin/static/My97DatePicker/skin/default/datepicker.css
owl_admin/static/My97DatePicker/skin/default/img.gif
owl_admin/static/My97DatePicker/skin/whyGreen/bg.jpg
owl_admin/static/My97DatePicker/skin/whyGreen/datepicker.css
owl_admin/static/My97DatePicker/skin/whyGreen/img.gif
owl_admin/static/My97DatePicker/开发包/readme.txt
owl_admin/static/My97DatePicker/开发包/lang/en.js
owl_admin/static/My97DatePicker/开发包/lang/zh-cn.js
owl_admin/static/My97DatePicker/开发包/lang/zh-tw.js
owl_admin/static/My97DatePicker/开发包/skin/WdatePicker.css
owl_admin/static/My97DatePicker/开发包/skin/datePicker.gif
owl_admin/static/My97DatePicker/开发包/skin/default/datepicker.css
owl_admin/static/My97DatePicker/开发包/skin/default/img.gif
owl_admin/static/My97DatePicker/开发包/skin/whyGreen/bg.jpg
owl_admin/static/My97DatePicker/开发包/skin/whyGreen/datepicker.css
owl_admin/static/My97DatePicker/开发包/skin/whyGreen/img.gif
owl_admin/static/owl_admin/fonts/glyphicons-halflings-regular.eot
owl_admin/static/owl_admin/fonts/glyphicons-halflings-regular.svg
owl_admin/static/owl_admin/fonts/glyphicons-halflings-regular.ttf
owl_admin/static/owl_admin/fonts/glyphicons-halflings-regular.woff
owl_admin/static/owl_admin/fonts/glyphicons-halflings-regular.woff2
owl_admin/static/owl_admin/scripts/bigtiger.js
owl_admin/static/owl_admin/scripts/bootstrap.js
owl_admin/static/owl_admin/scripts/owl.js
owl_admin/static/owl_admin/scripts/vendor.js
owl_admin/static/owl_admin/scripts/skin/default/icon-ext.png
