Metadata-Version: 2.0
Name: bigtiger-admin-owl
Version: 0.0.1rc2
Summary: bigtiger-admin-owl
Home-page: http://www.hshl.ltd
Author: bigtiger
Author-email: chinafengheping@gmail.com
License: UNKNOWN
Platform: UNKNOWN
Requires-Dist: bigtiger (>=0.3.8)
Requires-Dist: six
